{
  "activity_ad": [],
  "share_link": "https://m.yundong.runnerbar.com/#/activityDetail?activity_id=28874",
  "is_hidden_yd": 0,
  "QRCode": "https://oss.runnerbar.com/img/user_upload/qrcode/20231222/qrcode_28874.jpg",
  "activity": {
    "activity_id": 28874,
    "creater": 3166495,
    "title": "中国体育彩票杯·2024“红树林之城”湛江半程马拉松赛",
    "subtitle": null,
    "portal_pic": null,
    "poster": "https://oss.runnerbar.com/img/webview/_20240118164141_1705567301055.png",
    "share_poster": "https://oss.runnerbar.com/img/webview/_20240118165338_1705568018475.png",
    "share_activity_detail": "爱云动为你提供中国体育彩票杯·2024“红树林之城”湛江半程马拉松赛照片直播，速来围观~",
    "share_title": "中国体育彩票杯·2024“红树林之城”湛江半程马拉松赛",
    "start_time": 1705795215000,
    "end_time": 1705825780000,
    "album_type": 0,
    "is_live": 0,
    "is_subscribe": 1,
    "property": null,
    "match_type": -1,
    "is_english": 0,
    "status": 0,
    "activity_detail": "爱云动为你提供中国体育彩票杯·2024“红树林之城”湛江半程马拉松赛照片直播，速来围观~",
    "is_open_pay": 1,
    "pic_count": 436396,
    "visited_count": 52711,
    "video_count": 0,
    "is_faceSearch": 1,
    "is_need_tag": 2,
    "user_name": "爱云动套餐",
    "is_self_help": null,
    "field": "湛江",
    "is_open_translation": 1
  },
  "link": "http://m.yundong.runnerbar.com/yd_mobile/RR32ee/q",
  "video": 0,
  "competion_video_status": 0
}