{
  "has_order_package_info": 0,
  "result": {
    "bind_game_number": 1,
    "topicInfoList": [
      {
        "id": "5831132173909788657",
        "media_id": "5831132172744230769",
        "url": "https://oss.runnerbar.com/img/watermark/user_upload/origin/20231210/1702168481171_419bfbfd_01a2_4655_b18b_7496e9ae40d2.JPG",
        "url_lq": "https://oss.runnerbar.com/img/watermark/user_upload/origin/20231210/1702168481233_6f30be98_33a2_41ab_8772_724aac581c2c.JPG",
        "url_hq": "https://oss.runnerbar.com/img/watermark/user_upload/origin/20231210/1702168480932_26db0227_4deb_412f_8da1_abfe0fbaa098.JPG",
        "meta_info": "{\"DateTimeOriginal\":\"2023:12:10 08:15:20\",\"ImageHeight\":3456,\"ImageWidth\":5184,\"GPSLatitude\":31.29834,\"GPSLatitudeRef\":\"N\",\"GPSLongitude\":120.58319,\"GPSLongitudeRef\":\"E\",\"Orientation\":1,\"Make\":\"Canon\",\"Model\":\"Canon EOS-1D X\",\"MD5Original\":\"041937126b7a900ef42d7341c027e5f3\"}",
        "semblance": 0.0,
        "activity_id": 28734,
        "faceCoordLeft": 0,
        "faceCoordTop": 0,
        "faceCoordRight": 0,
        "faceCoordBottom": 0,
        "image_height": 3456,
        "image_width": 5184,
        "media_show_type": 1,
        "status": 1,
        "is_canbuy": 1,
        "standard_price": 100,
        "grade": 0,
        "sortValue": null,
        "searchType": null,
        "gps_latitude": 31.29834,
        "gps_longitude": 120.58319,
        "uid": 1200748,
        "orientation": 1
      },
      {
        "id": "5831273123462154179",
        "media_id": "5831273122282768354",
        "url": "https://oss.runnerbar.com/img/watermark/user_upload/origin/20231210/1702172681840_b371beff_517d_4ddb_bb78_541b029a8a20.JPG",
        "url_lq": "https://oss.runnerbar.com/img/watermark/user_upload/origin/20231210/1702172681911_8671c607_44c1_402d_8398_ad78f73360f4.JPG",
        "url_hq": "https://oss.runnerbar.com/img/watermark/user_upload/origin/20231210/1702172681556_feac0d35_30f4_416a_bb72_47e103549fef.JPG",
        "meta_info": "{\"DateTimeOriginal\":\"2023:12:10 08:14:55\",\"ImageHeight\":3648,\"ImageWidth\":5472,\"GPSLatitude\":31.29834,\"GPSLatitudeRef\":\"N\",\"GPSLongitude\":120.58319,\"GPSLongitudeRef\":\"E\",\"Orientation\":1,\"Make\":\"Canon\",\"Model\":\"Canon EOS-1D X Mark II\",\"MD5Original\":\"5bc34b7456eb688339d451cd186804f5\"}",
        "semblance": 0.0,
        "activity_id": 28734,
        "faceCoordLeft": 0,
        "faceCoordTop": 0,
        "faceCoordRight": 0,
        "faceCoordBottom": 0,
        "image_height": 3648,
        "image_width": 5472,
        "media_show_type": 1,
        "status": 1,
        "is_canbuy": 1,
        "standard_price": 100,
        "grade": 0,
        "sortValue": null,
        "searchType": null,
        "gps_latitude": 31.29834,
        "gps_longitude": 120.58319,
        "uid": 127870,
        "orientation": 1
      },
      {
        "id": "5831289734315286308",
        "media_id": "5831289733123645404",
        "url": "https://oss.runnerbar.com/img/watermark/user_upload/origin/20231210/1702173176833_6ac60c94_5b6e_4ba9_9048_1710989e6b72.jpg",
        "url_lq": "https://oss.runnerbar.com/img/watermark/user_upload/origin/20231210/1702173176887_1ecc5596_9abd_4eac_aa4f_860cbd368912.jpg",
        "url_hq": "https://oss.runnerbar.com/img/watermark/user_upload/origin/20231210/1702173176598_1967baaf_b7b3_4c4f_9aa2_3aedf06e6a68.jpg",
        "meta_info": "{\"DateTimeOriginal\":\"2023:12:10 09:37:04\",\"ImageHeight\":1600,\"ImageWidth\":2400,\"GPSLatitude\":31.29834,\"GPSLatitudeRef\":\"N\",\"GPSLongitude\":120.58319,\"GPSLongitudeRef\":\"E\",\"Orientation\":1,\"Make\":\"Canon\",\"Model\":\"Canon EOS R5\",\"MD5Original\":\"a95c81ec81ca579e3bb4825ee91a0f46\"}",
        "semblance": 0.0,
        "activity_id": 28734,
        "faceCoordLeft": 0,
        "faceCoordTop": 0,
        "faceCoordRight": 0,
        "faceCoordBottom": 0,
        "image_height": 1600,
        "image_width": 2400,
        "media_show_type": 1,
        "status": 1,
        "is_canbuy": 1,
        "standard_price": 100,
        "grade": 0,
        "sortValue": null,
        "searchType": null,
        "gps_latitude": 31.29834,
        "gps_longitude": 120.58319,
        "uid": 3398962,
        "orientation": 1
      },
      {
        "id": "5831289741965690688",
        "media_id": "5831289740903352161",
        "url": "https://oss.runnerbar.com/img/watermark/user_upload/origin/20231210/1702173177064_11e1aa66_d7dd_4a61_8298_54bc138d4bfb.jpg",
        "url_lq": "https://oss.runnerbar.com/img/watermark/user_upload/origin/20231210/1702173177119_9c3d34f7_295b_410b_904e_4651f9ee616b.jpg",
        "url_hq": "https://oss.runnerbar.com/img/watermark/user_upload/origin/20231210/1702173176826_73c394f2_5110_4993_84a7_c52e8590ca1d.jpg",
        "meta_info": "{\"DateTimeOriginal\":\"2023:12:10 09:37:04\",\"ImageHeight\":1600,\"ImageWidth\":2400,\"GPSLatitude\":31.29834,\"GPSLatitudeRef\":\"N\",\"GPSLongitude\":120.58319,\"GPSLongitudeRef\":\"E\",\"Orientation\":1,\"Make\":\"Canon\",\"Model\":\"Canon EOS R5\",\"MD5Original\":\"2caa6549bb526b73471f007b680485e9\"}",
        "semblance": 0.0,
        "activity_id": 28734,
        "faceCoordLeft": 0,
        "faceCoordTop": 0,
        "faceCoordRight": 0,
        "faceCoordBottom": 0,
        "image_height": 1600,
        "image_width": 2400,
        "media_show_type": 1,
        "status": 1,
        "is_canbuy": 1,
        "standard_price": 100,
        "grade": 0,
        "sortValue": null,
        "searchType": null,
        "gps_latitude": 31.29834,
        "gps_longitude": 120.58319,
        "uid": 3398962,
        "orientation": 1
      },
      {
        "id": "5831289742469013288",
        "media_id": "5831289741334847453",
        "url": "https://oss.runnerbar.com/img/watermark/user_upload/origin/20231210/1702173177078_cdaa2409_528b_465c_bd78_00f4154c35ae.jpg",
        "url_lq": "https://oss.runnerbar.com/img/watermark/user_upload/origin/20231210/1702173177150_b0d8f7c5_7825_4efc_b1ec_c7582a708a81.jpg",
        "url_hq": "https://oss.runnerbar.com/img/watermark/user_upload/origin/20231210/1702173176841_ec5fb43a_5626_4c35_9493_72c2d576165f.jpg",
        "meta_info": "{\"DateTimeOriginal\":\"2023:12:10 09:37:05\",\"ImageHeight\":1600,\"ImageWidth\":2400,\"GPSLatitude\":31.29834,\"GPSLatitudeRef\":\"N\",\"GPSLongitude\":120.58319,\"GPSLongitudeRef\":\"E\",\"Orientation\":1,\"Make\":\"Canon\",\"Model\":\"Canon EOS R5\",\"MD5Original\":\"20dfdf6aa0560eb42a50be39dcab302b\"}",
        "semblance": 0.0,
        "activity_id": 28734,
        "faceCoordLeft": 0,
        "faceCoordTop": 0,
        "faceCoordRight": 0,
        "faceCoordBottom": 0,
        "image_height": 1600,
        "image_width": 2400,
        "media_show_type": 1,
        "status": 1,
        "is_canbuy": 1,
        "standard_price": 100,
        "grade": 0,
        "sortValue": null,
        "searchType": null,
        "gps_latitude": 31.29834,
        "gps_longitude": 120.58319,
        "uid": 3398962,
        "orientation": 1
      },
      {
        "id": "5831289748307478448",
        "media_id": "5831289746816862143",
        "url": "https://oss.runnerbar.com/img/watermark/user_upload/origin/20231210/1702173177254_ab2d4287_04bc_42d2_a565_7717c7d4f7c9.jpg",
        "url_lq": "https://oss.runnerbar.com/img/watermark/user_upload/origin/20231210/1702173177310_45a23edf_0496_4b61_95d1_e1b141faaade.jpg",
        "url_hq": "https://oss.runnerbar.com/img/watermark/user_upload/origin/20231210/1702173177015_5e2a3b7e_ebdc_4a83_9859_5423ae1924d7.jpg",
        "meta_info": "{\"DateTimeOriginal\":\"2023:12:10 09:37:06\",\"ImageHeight\":1600,\"ImageWidth\":2400,\"GPSLatitude\":31.29834,\"GPSLatitudeRef\":\"N\",\"GPSLongitude\":120.58319,\"GPSLongitudeRef\":\"E\",\"Orientation\":1,\"Make\":\"Canon\",\"Model\":\"Canon EOS R5\",\"MD5Original\":\"30a029eb054672b5b52883a942753b43\"}",
        "semblance": 0.0,
        "activity_id": 28734,
        "faceCoordLeft": 0,
        "faceCoordTop": 0,
        "faceCoordRight": 0,
        "faceCoordBottom": 0,
        "image_height": 1600,
        "image_width": 2400,
        "media_show_type": 1,
        "status": 1,
        "is_canbuy": 1,
        "standard_price": 100,
        "grade": 0,
        "sortValue": null,
        "searchType": null,
        "gps_latitude": 31.29834,
        "gps_longitude": 120.58319,
        "uid": 3398962,
        "orientation": 1
      },
      {
        "id": "5831289755655905175",
        "media_id": "5831289754504437679",
        "url": "https://oss.runnerbar.com/img/watermark/user_upload/origin/20231210/1702173177478_720c4e67_6d0f_4709_bcaa_d94d2f66bb79.jpg",
        "url_lq": "https://oss.runnerbar.com/img/watermark/user_upload/origin/20231210/1702173177537_e78a67c5_f010_4ca7_8f80_344ca6441353.jpg",
        "url_hq": "https://oss.runnerbar.com/img/watermark/user_upload/origin/20231210/1702173177234_e4b88751_2a32_4b98_bfb7_947096096024.jpg",
        "meta_info": "{\"DateTimeOriginal\":\"2023:12:10 09:37:06\",\"ImageHeight\":1600,\"ImageWidth\":2400,\"GPSLatitude\":31.29834,\"GPSLatitudeRef\":\"N\",\"GPSLongitude\":120.58319,\"GPSLongitudeRef\":\"E\",\"Orientation\":1,\"Make\":\"Canon\",\"Model\":\"Canon EOS R5\",\"MD5Original\":\"e2dae84ac62cd70616e67a8e418f2da4\"}",
        "semblance": 0.0,
        "activity_id": 28734,
        "faceCoordLeft": 0,
        "faceCoordTop": 0,
        "faceCoordRight": 0,
        "faceCoordBottom": 0,
        "image_height": 1600,
        "image_width": 2400,
        "media_show_type": 1,
        "status": 1,
        "is_canbuy": 1,
        "standard_price": 100,
        "grade": 0,
        "sortValue": null,
        "searchType": null,
        "gps_latitude": 31.29834,
        "gps_longitude": 120.58319,
        "uid": 3398962,
        "orientation": 1
      },
      {
        "id": "5831289757098745654",
        "media_id": "5831289755970346978",
        "url": "https://oss.runnerbar.com/img/watermark/user_upload/origin/20231210/1702173177492_b6008395_49a3_4383_81a6_0d465bc59cd2.jpg",
        "url_lq": "https://oss.runnerbar.com/img/watermark/user_upload/origin/20231210/1702173177556_a80f93ab_caa8_497e_b2e1_5bc75a3d0a5f.jpg",
        "url_hq": "https://oss.runnerbar.com/img/watermark/user_upload/origin/20231210/1702173177277_b0e67af2_7582_4581_b64d_206ad38816fa.jpg",
        "meta_info": "{\"DateTimeOriginal\":\"2023:12:10 09:37:08\",\"ImageHeight\":1600,\"ImageWidth\":2400,\"GPSLatitude\":31.29834,\"GPSLatitudeRef\":\"N\",\"GPSLongitude\":120.58319,\"GPSLongitudeRef\":\"E\",\"Orientation\":1,\"Make\":\"Canon\",\"Model\":\"Canon EOS R5\",\"MD5Original\":\"ebfa5c0c2a99e3c74d9634d9ee0ef1b9\"}",
        "semblance": 0.0,
        "activity_id": 28734,
        "faceCoordLeft": 0,
        "faceCoordTop": 0,
        "faceCoordRight": 0,
        "faceCoordBottom": 0,
        "image_height": 1600,
        "image_width": 2400,
        "media_show_type": 1,
        "status": 1,
        "is_canbuy": 1,
        "standard_price": 100,
        "grade": 0,
        "sortValue": null,
        "searchType": null,
        "gps_latitude": 31.29834,
        "gps_longitude": 120.58319,
        "uid": 3398962,
        "orientation": 1
      },
      {
        "id": "5831289835314126655",
        "media_id": "5831289834147258345",
        "url": "https://oss.runnerbar.com/img/watermark/user_upload/origin/20231210/1702173179839_a9ff8516_1913_41c6_857c_4c3add60ac95.jpg",
        "url_lq": "https://oss.runnerbar.com/img/watermark/user_upload/origin/20231210/1702173179895_a248d1ac_4122_4221_b0b0_cd71874fa531.jpg",
        "url_hq": "https://oss.runnerbar.com/img/watermark/user_upload/origin/20231210/1702173179608_edf4fadf_c281_43a9_a456_b7ea622f9886.jpg",
        "meta_info": "{\"DateTimeOriginal\":\"2023:12:10 09:37:08\",\"ImageHeight\":1600,\"ImageWidth\":2400,\"GPSLatitude\":31.29834,\"GPSLatitudeRef\":\"N\",\"GPSLongitude\":120.58319,\"GPSLongitudeRef\":\"E\",\"Orientation\":1,\"Make\":\"Canon\",\"Model\":\"Canon EOS R5\",\"MD5Original\":\"e7ee7e5510ae33bbda1eacbed02ef47b\"}",
        "semblance": 0.0,
        "activity_id": 28734,
        "faceCoordLeft": 0,
        "faceCoordTop": 0,
        "faceCoordRight": 0,
        "faceCoordBottom": 0,
        "image_height": 1600,
        "image_width": 2400,
        "media_show_type": 1,
        "status": 1,
        "is_canbuy": 1,
        "standard_price": 100,
        "grade": 0,
        "sortValue": null,
        "searchType": null,
        "gps_latitude": 31.29834,
        "gps_longitude": 120.58319,
        "uid": 3398962,
        "orientation": 1
      },
      {
        "id": "5831291609437603393",
        "media_id": "5831291608365893133",
        "url": "https://oss.runnerbar.com/img/watermark/user_upload/origin/20231210/1702173232735_72b75e3a_ec0d_4853_a2a3_6b76e0b6da09.JPG",
        "url_lq": "https://oss.runnerbar.com/img/watermark/user_upload/origin/20231210/1702173232809_69a462b3_7a62_4039_b3a9_a30b08ad3ea6.JPG",
        "url_hq": "https://oss.runnerbar.com/img/watermark/user_upload/origin/20231210/1702173232481_58bec5da_7a61_4bc5_9d19_3da8da4f767f.JPG",
        "meta_info": "{\"DateTimeOriginal\":\"2023:12:10 09:29:03\",\"ImageHeight\":3872,\"ImageWidth\":5808,\"GPSLatitude\":31.29834,\"GPSLatitudeRef\":\"N\",\"GPSLongitude\":120.58319,\"GPSLongitudeRef\":\"E\",\"Orientation\":8,\"Make\":\"Canon\",\"Model\":\"Canon EOS R5\",\"MD5Original\":\"97645459f63d05af34d10789f61b01cd\"}",
        "semblance": 0.0,
        "activity_id": 28734,
        "faceCoordLeft": 0,
        "faceCoordTop": 0,
        "faceCoordRight": 0,
        "faceCoordBottom": 0,
        "image_height": 3872,
        "image_width": 5808,
        "media_show_type": 1,
        "status": 1,
        "is_canbuy": 1,
        "standard_price": 100,
        "grade": 0,
        "sortValue": null,
        "searchType": null,
        "gps_latitude": 31.29834,
        "gps_longitude": 120.58319,
        "uid": 916968,
        "orientation": 8
      },
      {
        "id": "5831291632254623615",
        "media_id": "5831291631121309613",
        "url": "https://oss.runnerbar.com/img/watermark/user_upload/origin/20231210/1702173233428_d3e9a4f1_7e45_4223_9cb3_c67c6066cb23.JPG",
        "url_lq": "https://oss.runnerbar.com/img/watermark/user_upload/origin/20231210/1702173233517_92717ecd_2908_44ca_8a71_a2f7657016c2.JPG",
        "url_hq": "https://oss.runnerbar.com/img/watermark/user_upload/origin/20231210/1702173233161_2a875074_aede_4457_b9aa_b00bd5683917.JPG",
        "meta_info": "{\"DateTimeOriginal\":\"2023:12:10 09:29:03\",\"ImageHeight\":3872,\"ImageWidth\":5808,\"GPSLatitude\":31.29834,\"GPSLatitudeRef\":\"N\",\"GPSLongitude\":120.58319,\"GPSLongitudeRef\":\"E\",\"Orientation\":8,\"Make\":\"Canon\",\"Model\":\"Canon EOS R5\",\"MD5Original\":\"e28e693f2c004206fac852f045f84259\"}",
        "semblance": 0.0,
        "activity_id": 28734,
        "faceCoordLeft": 0,
        "faceCoordTop": 0,
        "faceCoordRight": 0,
        "faceCoordBottom": 0,
        "image_height": 3872,
        "image_width": 5808,
        "media_show_type": 1,
        "status": 1,
        "is_canbuy": 1,
        "standard_price": 100,
        "grade": 0,
        "sortValue": null,
        "searchType": null,
        "gps_latitude": 31.29834,
        "gps_longitude": 120.58319,
        "uid": 916968,
        "orientation": 8
      },
      {
        "id": "5831291660910102496",
        "media_id": "5831291659757193208",
        "url": "https://oss.runnerbar.com/img/watermark/user_upload/origin/20231210/1702173234290_1d8f2d59_02d7_471f_8a2a_ba18c5473e00.JPG",
        "url_lq": "https://oss.runnerbar.com/img/watermark/user_upload/origin/20231210/1702173234366_db987366_f406_4ccd_a5c8_98712c4b4e0e.JPG",
        "url_hq": "https://oss.runnerbar.com/img/watermark/user_upload/origin/20231210/1702173234015_4186f17b_0fc4_49fb_9df8_e4b393977a69.JPG",
        "meta_info": "{\"DateTimeOriginal\":\"2023:12:10 09:29:04\",\"ImageHeight\":3872,\"ImageWidth\":5808,\"GPSLatitude\":31.29834,\"GPSLatitudeRef\":\"N\",\"GPSLongitude\":120.58319,\"GPSLongitudeRef\":\"E\",\"Orientation\":8,\"Make\":\"Canon\",\"Model\":\"Canon EOS R5\",\"MD5Original\":\"fd2ec2cf1131ed0045ecd85aaf8c6c75\"}",
        "semblance": 0.0,
        "activity_id": 28734,
        "faceCoordLeft": 0,
        "faceCoordTop": 0,
        "faceCoordRight": 0,
        "faceCoordBottom": 0,
        "image_height": 3872,
        "image_width": 5808,
        "media_show_type": 1,
        "status": 1,
        "is_canbuy": 1,
        "standard_price": 100,
        "grade": 0,
        "sortValue": null,
        "searchType": null,
        "gps_latitude": 31.29834,
        "gps_longitude": 120.58319,
        "uid": 916968,
        "orientation": 8
      },
      {
        "id": "5831291688760287173",
        "media_id": "5831291687578214332",
        "url": "https://oss.runnerbar.com/img/watermark/user_upload/origin/20231210/1702173235075_e4bc9462_7be7_4388_b810_5c053945c845.JPG",
        "url_lq": "https://oss.runnerbar.com/img/watermark/user_upload/origin/20231210/1702173235136_9d850581_a473_484a_9e66_a06f287d6657.JPG",
        "url_hq": "https://oss.runnerbar.com/img/watermark/user_upload/origin/20231210/1702173234845_bab18abf_5049_43c3_ac76_74601bd07a55.JPG",
        "meta_info": "{\"DateTimeOriginal\":\"2023:12:10 09:29:04\",\"ImageHeight\":3872,\"ImageWidth\":5808,\"GPSLatitude\":31.29834,\"GPSLatitudeRef\":\"N\",\"GPSLongitude\":120.58319,\"GPSLongitudeRef\":\"E\",\"Orientation\":8,\"Make\":\"Canon\",\"Model\":\"Canon EOS R5\",\"MD5Original\":\"8fd6e13fea937b8ef76302b31fa53d3b\"}",
        "semblance": 0.0,
        "activity_id": 28734,
        "faceCoordLeft": 0,
        "faceCoordTop": 0,
        "faceCoordRight": 0,
        "faceCoordBottom": 0,
        "image_height": 3872,
        "image_width": 5808,
        "media_show_type": 1,
        "status": 1,
        "is_canbuy": 1,
        "standard_price": 100,
        "grade": 0,
        "sortValue": null,
        "searchType": null,
        "gps_latitude": 31.29834,
        "gps_longitude": 120.58319,
        "uid": 916968,
        "orientation": 8
      },
      {
        "id": "5831291713389240177",
        "media_id": "5831291711977201657",
        "url": "https://oss.runnerbar.com/img/watermark/user_upload/origin/20231210/1702173235817_05884e24_5896_4242_a101_34d984b3eb71.JPG",
        "url_lq": "https://oss.runnerbar.com/img/watermark/user_upload/origin/20231210/1702173235875_484f66ce_18e3_4e42_878e_7e77cf224822.JPG",
        "url_hq": "https://oss.runnerbar.com/img/watermark/user_upload/origin/20231210/1702173235579_c59c9814_15d4_4e19_8f48_85d5121a8d70.JPG",
        "meta_info": "{\"DateTimeOriginal\":\"2023:12:10 09:29:04\",\"ImageHeight\":3872,\"ImageWidth\":5808,\"GPSLatitude\":31.29834,\"GPSLatitudeRef\":\"N\",\"GPSLongitude\":120.58319,\"GPSLongitudeRef\":\"E\",\"Orientation\":8,\"Make\":\"Canon\",\"Model\":\"Canon EOS R5\",\"MD5Original\":\"500ee08ec568fd19627e240ec1555833\"}",
        "semblance": 0.0,
        "activity_id": 28734,
        "faceCoordLeft": 0,
        "faceCoordTop": 0,
        "faceCoordRight": 0,
        "faceCoordBottom": 0,
        "image_height": 3872,
        "image_width": 5808,
        "media_show_type": 1,
        "status": 1,
        "is_canbuy": 1,
        "standard_price": 100,
        "grade": 0,
        "sortValue": null,
        "searchType": null,
        "gps_latitude": 31.29834,
        "gps_longitude": 120.58319,
        "uid": 916968,
        "orientation": 8
      },
      {
        "id": "5831291733219903382",
        "media_id": "5831291732117784531",
        "url": "https://oss.runnerbar.com/img/watermark/user_upload/origin/20231210/1702173236422_b7770cb9_b15f_4e9b_8022_d5eff4fd74be.JPG",
        "url_lq": "https://oss.runnerbar.com/img/watermark/user_upload/origin/20231210/1702173236489_61fbc745_6320_47ee_b5b5_46949a3f0823.JPG",
        "url_hq": "https://oss.runnerbar.com/img/watermark/user_upload/origin/20231210/1702173236170_9f3bcc2d_77ee_4b81_9cf8_d508b96458b8.JPG",
        "meta_info": "{\"DateTimeOriginal\":\"2023:12:10 09:29:04\",\"ImageHeight\":3872,\"ImageWidth\":5808,\"GPSLatitude\":31.29834,\"GPSLatitudeRef\":\"N\",\"GPSLongitude\":120.58319,\"GPSLongitudeRef\":\"E\",\"Orientation\":8,\"Make\":\"Canon\",\"Model\":\"Canon EOS R5\",\"MD5Original\":\"bd6b5a26fd6e3c41fd1d643dbb11a853\"}",
        "semblance": 0.0,
        "activity_id": 28734,
        "faceCoordLeft": 0,
        "faceCoordTop": 0,
        "faceCoordRight": 0,
        "faceCoordBottom": 0,
        "image_height": 3872,
        "image_width": 5808,
        "media_show_type": 1,
        "status": 1,
        "is_canbuy": 1,
        "standard_price": 100,
        "grade": 0,
        "sortValue": null,
        "searchType": null,
        "gps_latitude": 31.29834,
        "gps_longitude": 120.58319,
        "uid": 916968,
        "orientation": 8
      },
      {
        "id": "5831291761002979223",
        "media_id": "5831291759828311815",
        "url": "https://oss.runnerbar.com/img/watermark/user_upload/origin/20231210/1702173237292_de6f64f3_49f2_4b67_9bd8_b96e4ff02f9a.JPG",
        "url_lq": "https://oss.runnerbar.com/img/watermark/user_upload/origin/20231210/1702173237348_03c949f2_ee62_4beb_b16e_19322521d6b4.JPG",
        "url_hq": "https://oss.runnerbar.com/img/watermark/user_upload/origin/20231210/1702173236998_45a0abe4_8311_43f1_bfbb_210f88af1b65.JPG",
        "meta_info": "{\"DateTimeOriginal\":\"2023:12:10 09:29:05\",\"ImageHeight\":3872,\"ImageWidth\":5808,\"GPSLatitude\":31.29834,\"GPSLatitudeRef\":\"N\",\"GPSLongitude\":120.58319,\"GPSLongitudeRef\":\"E\",\"Orientation\":8,\"Make\":\"Canon\",\"Model\":\"Canon EOS R5\",\"MD5Original\":\"b7197107c45dc531b0232232b361386c\"}",
        "semblance": 0.0,
        "activity_id": 28734,
        "faceCoordLeft": 0,
        "faceCoordTop": 0,
        "faceCoordRight": 0,
        "faceCoordBottom": 0,
        "image_height": 3872,
        "image_width": 5808,
        "media_show_type": 1,
        "status": 1,
        "is_canbuy": 1,
        "standard_price": 100,
        "grade": 0,
        "sortValue": null,
        "searchType": null,
        "gps_latitude": 31.29834,
        "gps_longitude": 120.58319,
        "uid": 916968,
        "orientation": 8
      },
      {
        "id": "5831291787913627523",
        "media_id": "5831291786763012016",
        "url": "https://oss.runnerbar.com/img/watermark/user_upload/origin/20231210/1702173238045_9449777d_d500_4351_b234_16ed68a37a88.JPG",
        "url_lq": "https://oss.runnerbar.com/img/watermark/user_upload/origin/20231210/1702173238113_5a3fdb24_4177_4590_971f_908f411ca1d8.JPG",
        "url_hq": "https://oss.runnerbar.com/img/watermark/user_upload/origin/20231210/1702173237800_f9dcde21_e780_483c_aa12_182d01241f9f.JPG",
        "meta_info": "{\"DateTimeOriginal\":\"2023:12:10 09:29:05\",\"ImageHeight\":3872,\"ImageWidth\":5808,\"GPSLatitude\":31.29834,\"GPSLatitudeRef\":\"N\",\"GPSLongitude\":120.58319,\"GPSLongitudeRef\":\"E\",\"Orientation\":8,\"Make\":\"Canon\",\"Model\":\"Canon EOS R5\",\"MD5Original\":\"f6a6e73154315d39cb480e0342b9c68e\"}",
        "semblance": 0.0,
        "activity_id": 28734,
        "faceCoordLeft": 0,
        "faceCoordTop": 0,
        "faceCoordRight": 0,
        "faceCoordBottom": 0,
        "image_height": 3872,
        "image_width": 5808,
        "media_show_type": 1,
        "status": 1,
        "is_canbuy": 1,
        "standard_price": 100,
        "grade": 0,
        "sortValue": null,
        "searchType": null,
        "gps_latitude": 31.29834,
        "gps_longitude": 120.58319,
        "uid": 916968,
        "orientation": 8
      },
      {
        "id": "5831291807408752490",
        "media_id": "5831291806272292721",
        "url": "https://oss.runnerbar.com/img/watermark/user_upload/origin/20231210/1702173238634_7c7ed3b6_ca21_48f9_81d0_6d4e61fa52a2.JPG",
        "url_lq": "https://oss.runnerbar.com/img/watermark/user_upload/origin/20231210/1702173238686_1dcf5237_764a_41f7_9795_3046039122cb.JPG",
        "url_hq": "https://oss.runnerbar.com/img/watermark/user_upload/origin/20231210/1702173238381_3a178084_60c7_4725_9cd1_591ee3f6d073.JPG",
        "meta_info": "{\"DateTimeOriginal\":\"2023:12:10 09:29:05\",\"ImageHeight\":3872,\"ImageWidth\":5808,\"GPSLatitude\":31.29834,\"GPSLatitudeRef\":\"N\",\"GPSLongitude\":120.58319,\"GPSLongitudeRef\":\"E\",\"Orientation\":8,\"Make\":\"Canon\",\"Model\":\"Canon EOS R5\",\"MD5Original\":\"9c5347131fa3ff662f729cc3f0a098f0\"}",
        "semblance": 0.0,
        "activity_id": 28734,
        "faceCoordLeft": 0,
        "faceCoordTop": 0,
        "faceCoordRight": 0,
        "faceCoordBottom": 0,
        "image_height": 3872,
        "image_width": 5808,
        "media_show_type": 1,
        "status": 1,
        "is_canbuy": 1,
        "standard_price": 100,
        "grade": 0,
        "sortValue": null,
        "searchType": null,
        "gps_latitude": 31.29834,
        "gps_longitude": 120.58319,
        "uid": 916968,
        "orientation": 8
      },
      {
        "id": "5831291832843011592",
        "media_id": "5831291831657596495",
        "url": "https://oss.runnerbar.com/img/watermark/user_upload/origin/20231210/1702173239379_63ddbb0d_ef8e_46c1_a19a_5486ab32da3b.JPG",
        "url_lq": "https://oss.runnerbar.com/img/watermark/user_upload/origin/20231210/1702173239438_5eff9c75_8eb1_402e_98a0_5aa35af6368a.JPG",
        "url_hq": "https://oss.runnerbar.com/img/watermark/user_upload/origin/20231210/1702173239139_df564706_edb1_4857_93ba_14d301cbcb83.JPG",
        "meta_info": "{\"DateTimeOriginal\":\"2023:12:10 09:29:05\",\"ImageHeight\":3872,\"ImageWidth\":5808,\"GPSLatitude\":31.29834,\"GPSLatitudeRef\":\"N\",\"GPSLongitude\":120.58319,\"GPSLongitudeRef\":\"E\",\"Orientation\":8,\"Make\":\"Canon\",\"Model\":\"Canon EOS R5\",\"MD5Original\":\"14a2c940884a06b154c821328268a34b\"}",
        "semblance": 0.0,
        "activity_id": 28734,
        "faceCoordLeft": 0,
        "faceCoordTop": 0,
        "faceCoordRight": 0,
        "faceCoordBottom": 0,
        "image_height": 3872,
        "image_width": 5808,
        "media_show_type": 1,
        "status": 1,
        "is_canbuy": 1,
        "standard_price": 100,
        "grade": 0,
        "sortValue": null,
        "searchType": null,
        "gps_latitude": 31.29834,
        "gps_longitude": 120.58319,
        "uid": 916968,
        "orientation": 8
      },
      {
        "id": "5831291859820774946",
        "media_id": "5831291858650695256",
        "url": "https://oss.runnerbar.com/img/watermark/user_upload/origin/20231210/1702173240195_8924e2b6_b68f_4810_9e7e_498d1c878366.JPG",
        "url_lq": "https://oss.runnerbar.com/img/watermark/user_upload/origin/20231210/1702173240258_cecedadf_2afc_451f_91b6_e9bf2ee096f4.JPG",
        "url_hq": "https://oss.runnerbar.com/img/watermark/user_upload/origin/20231210/1702173239943_08f4be12_7abb_4deb_9226_a16ba47e7594.JPG",
        "meta_info": "{\"DateTimeOriginal\":\"2023:12:10 09:29:05\",\"ImageHeight\":3872,\"ImageWidth\":5808,\"GPSLatitude\":31.29834,\"GPSLatitudeRef\":\"N\",\"GPSLongitude\":120.58319,\"GPSLongitudeRef\":\"E\",\"Orientation\":8,\"Make\":\"Canon\",\"Model\":\"Canon EOS R5\",\"MD5Original\":\"13efa419b34853633712c7da92d3695f\"}",
        "semblance": 0.0,
        "activity_id": 28734,
        "faceCoordLeft": 0,
        "faceCoordTop": 0,
        "faceCoordRight": 0,
        "faceCoordBottom": 0,
        "image_height": 3872,
        "image_width": 5808,
        "media_show_type": 1,
        "status": 1,
        "is_canbuy": 1,
        "standard_price": 100,
        "grade": 0,
        "sortValue": null,
        "searchType": null,
        "gps_latitude": 31.29834,
        "gps_longitude": 120.58319,
        "uid": 916968,
        "orientation": 8
      },
      {
        "id": "5831294730704428913",
        "media_id": "5831294729430081442",
        "url": "https://oss.runnerbar.com/img/watermark/user_upload/origin/20231210/1702173325743_ba29c6e9_9fcf_4c6b_8740_f4f88a887cf4.JPG",
        "url_lq": "https://oss.runnerbar.com/img/watermark/user_upload/origin/20231210/1702173325807_822f3684_5e56_461d_9a65_0d08e3afa7ce.JPG",
        "url_hq": "https://oss.runnerbar.com/img/watermark/user_upload/origin/20231210/1702173325502_7d52f497_00a0_4ab5_a30d_b418910c97f2.JPG",
        "meta_info": "{\"DateTimeOriginal\":\"2023:12:10 09:23:43\",\"ImageHeight\":3456,\"ImageWidth\":5184,\"GPSLatitude\":31.29834,\"GPSLatitudeRef\":\"N\",\"GPSLongitude\":120.58319,\"GPSLongitudeRef\":\"E\",\"Orientation\":8,\"Make\":\"Canon\",\"Model\":\"Canon EOS-1D X\",\"MD5Original\":\"e67fee47d5ad0d369d40f327a60cb082\"}",
        "semblance": 0.0,
        "activity_id": 28734,
        "faceCoordLeft": 0,
        "faceCoordTop": 0,
        "faceCoordRight": 0,
        "faceCoordBottom": 0,
        "image_height": 3456,
        "image_width": 5184,
        "media_show_type": 1,
        "status": 1,
        "is_canbuy": 1,
        "standard_price": 100,
        "grade": 0,
        "sortValue": null,
        "searchType": null,
        "gps_latitude": 31.29834,
        "gps_longitude": 120.58319,
        "uid": 1200748,
        "orientation": 8
      },
      {
        "id": "5831391358207559456",
        "media_id": "5831391356988655368",
        "url": "https://oss.runnerbar.com/img/watermark/user_upload/origin/20231210/1702176205463_7f5f54ae_1e2c_4708_8e1f_2054f8073ee5.JPG",
        "url_lq": "https://oss.runnerbar.com/img/watermark/user_upload/origin/20231210/1702176205521_d567a3b0_f5e9_4908_98f3_a6c15822cd8a.JPG",
        "url_hq": "https://oss.runnerbar.com/img/watermark/user_upload/origin/20231210/1702176205226_2325f193_b79d_4a25_b994_7583e3bcf66f.JPG",
        "meta_info": "{\"DateTimeOriginal\":\"2023:12:10 09:51:46\",\"ImageHeight\":4480,\"ImageWidth\":6720,\"GPSLatitude\":31.29834,\"GPSLatitudeRef\":\"N\",\"GPSLongitude\":120.58319,\"GPSLongitudeRef\":\"E\",\"Orientation\":8,\"Make\":\"Canon\",\"Model\":\"Canon EOS 5D Mark IV\",\"MD5Original\":\"c2a0278b73736470b86a85b379e9705d\"}",
        "semblance": 0.0,
        "activity_id": 28734,
        "faceCoordLeft": 0,
        "faceCoordTop": 0,
        "faceCoordRight": 0,
        "faceCoordBottom": 0,
        "image_height": 4480,
        "image_width": 6720,
        "media_show_type": 1,
        "status": 1,
        "is_canbuy": 1,
        "standard_price": 100,
        "grade": 0,
        "sortValue": null,
        "searchType": null,
        "gps_latitude": 31.29834,
        "gps_longitude": 120.58319,
        "uid": 127870,
        "orientation": 8
      },
      {
        "id": "5831391383373383451",
        "media_id": "5831391382203303814",
        "url": "https://oss.runnerbar.com/img/watermark/user_upload/origin/20231210/1702176206225_715008c8_12e7_4cbc_9ec2_c80c358a5d0a.JPG",
        "url_lq": "https://oss.runnerbar.com/img/watermark/user_upload/origin/20231210/1702176206309_dabc4f0e_42c8_4376_8813_c94c1dd1532e.JPG",
        "url_hq": "https://oss.runnerbar.com/img/watermark/user_upload/origin/20231210/1702176205976_00d52f61_50cf_4e42_aa1e_5a1f9583a536.JPG",
        "meta_info": "{\"DateTimeOriginal\":\"2023:12:10 09:51:46\",\"ImageHeight\":4480,\"ImageWidth\":6720,\"GPSLatitude\":31.29834,\"GPSLatitudeRef\":\"N\",\"GPSLongitude\":120.58319,\"GPSLongitudeRef\":\"E\",\"Orientation\":8,\"Make\":\"Canon\",\"Model\":\"Canon EOS 5D Mark IV\",\"MD5Original\":\"40dbadafc5d32d967c60523b45fb78ec\"}",
        "semblance": 0.0,
        "activity_id": 28734,
        "faceCoordLeft": 0,
        "faceCoordTop": 0,
        "faceCoordRight": 0,
        "faceCoordBottom": 0,
        "image_height": 4480,
        "image_width": 6720,
        "media_show_type": 1,
        "status": 1,
        "is_canbuy": 1,
        "standard_price": 100,
        "grade": 0,
        "sortValue": null,
        "searchType": null,
        "gps_latitude": 31.29834,
        "gps_longitude": 120.58319,
        "uid": 127870,
        "orientation": 8
      },
      {
        "id": "5831391469071402797",
        "media_id": "5831391467895687012",
        "url": "https://oss.runnerbar.com/img/watermark/user_upload/origin/20231210/1702176208792_b2858e66_f9f0_4985_be4e_8bfb4b74f179.JPG",
        "url_lq": "https://oss.runnerbar.com/img/watermark/user_upload/origin/20231210/1702176208870_80e0bb62_54a9_4dc5_85c3_f7f4b23cfa1c.JPG",
        "url_hq": "https://oss.runnerbar.com/img/watermark/user_upload/origin/20231210/1702176208531_d0264ab8_798f_430d_933a_9abf760d6755.JPG",
        "meta_info": "{\"DateTimeOriginal\":\"2023:12:10 09:51:47\",\"ImageHeight\":4480,\"ImageWidth\":6720,\"GPSLatitude\":31.29834,\"GPSLatitudeRef\":\"N\",\"GPSLongitude\":120.58319,\"GPSLongitudeRef\":\"E\",\"Orientation\":8,\"Make\":\"Canon\",\"Model\":\"Canon EOS 5D Mark IV\",\"MD5Original\":\"c19ec2f0ea0885deb7c5d66819a2cc23\"}",
        "semblance": 0.0,
        "activity_id": 28734,
        "faceCoordLeft": 0,
        "faceCoordTop": 0,
        "faceCoordRight": 0,
        "faceCoordBottom": 0,
        "image_height": 4480,
        "image_width": 6720,
        "media_show_type": 1,
        "status": 1,
        "is_canbuy": 1,
        "standard_price": 100,
        "grade": 0,
        "sortValue": null,
        "searchType": null,
        "gps_latitude": 31.29834,
        "gps_longitude": 120.58319,
        "uid": 127870,
        "orientation": 8
      },
      {
        "id": "5831391491385100086",
        "media_id": "5831391490175502183",
        "url": "https://oss.runnerbar.com/img/watermark/user_upload/origin/20231210/1702176209439_b0720c0e_a296_42ed_9a2b_12fa5e6bd997.JPG",
        "url_lq": "https://oss.runnerbar.com/img/watermark/user_upload/origin/20231210/1702176209521_7d38f5ec_aa04_401d_bfb2_498c86279020.JPG",
        "url_hq": "https://oss.runnerbar.com/img/watermark/user_upload/origin/20231210/1702176209195_9ed7b3ac_16b2_4165_8c90_7c675b24935e.JPG",
        "meta_info": "{\"DateTimeOriginal\":\"2023:12:10 09:51:48\",\"ImageHeight\":4480,\"ImageWidth\":6720,\"GPSLatitude\":31.29834,\"GPSLatitudeRef\":\"N\",\"GPSLongitude\":120.58319,\"GPSLongitudeRef\":\"E\",\"Orientation\":8,\"Make\":\"Canon\",\"Model\":\"Canon EOS 5D Mark IV\",\"MD5Original\":\"61af571cdb6adc36f03455528512acca\"}",
        "semblance": 0.0,
        "activity_id": 28734,
        "faceCoordLeft": 0,
        "faceCoordTop": 0,
        "faceCoordRight": 0,
        "faceCoordBottom": 0,
        "image_height": 4480,
        "image_width": 6720,
        "media_show_type": 1,
        "status": 1,
        "is_canbuy": 1,
        "standard_price": 100,
        "grade": 0,
        "sortValue": null,
        "searchType": null,
        "gps_latitude": 31.29834,
        "gps_longitude": 120.58319,
        "uid": 127870,
        "orientation": 8
      },
      {
        "id": "5831391515879841641",
        "media_id": "5831391514529079147",
        "url": "https://oss.runnerbar.com/img/watermark/user_upload/origin/20231210/1702176210172_3edf8380_32f9_4799_a4b8_5f916732e866.JPG",
        "url_lq": "https://oss.runnerbar.com/img/watermark/user_upload/origin/20231210/1702176210232_6f8516b7_b857_4c70_be5c_7d754b8a0b0c.JPG",
        "url_hq": "https://oss.runnerbar.com/img/watermark/user_upload/origin/20231210/1702176209925_8c9eeb6b_ffc4_4391_aa51_af248f95b27e.JPG",
        "meta_info": "{\"DateTimeOriginal\":\"2023:12:10 09:51:48\",\"ImageHeight\":4480,\"ImageWidth\":6720,\"GPSLatitude\":31.29834,\"GPSLatitudeRef\":\"N\",\"GPSLongitude\":120.58319,\"GPSLongitudeRef\":\"E\",\"Orientation\":8,\"Make\":\"Canon\",\"Model\":\"Canon EOS 5D Mark IV\",\"MD5Original\":\"f69aae81d59e875778ea026559d2dfee\"}",
        "semblance": 0.0,
        "activity_id": 28734,
        "faceCoordLeft": 0,
        "faceCoordTop": 0,
        "faceCoordRight": 0,
        "faceCoordBottom": 0,
        "image_height": 4480,
        "image_width": 6720,
        "media_show_type": 1,
        "status": 1,
        "is_canbuy": 1,
        "standard_price": 100,
        "grade": 0,
        "sortValue": null,
        "searchType": null,
        "gps_latitude": 31.29834,
        "gps_longitude": 120.58319,
        "uid": 127870,
        "orientation": 8
      },
      {
        "id": "5831391538898175875",
        "media_id": "5831391537733011332",
        "url": "https://oss.runnerbar.com/img/watermark/user_upload/origin/20231210/1702176210845_58d4e76d_a5e9_4294_b3cf_46a4c5c090b7.JPG",
        "url_lq": "https://oss.runnerbar.com/img/watermark/user_upload/origin/20231210/1702176210902_2442b798_38ec_4c38_ab40_9820529e45e1.JPG",
        "url_hq": "https://oss.runnerbar.com/img/watermark/user_upload/origin/20231210/1702176210611_73944994_a3e0_45ab_a9e6_a3f680fb2c67.JPG",
        "meta_info": "{\"DateTimeOriginal\":\"2023:12:10 09:51:48\",\"ImageHeight\":4480,\"ImageWidth\":6720,\"GPSLatitude\":31.29834,\"GPSLatitudeRef\":\"N\",\"GPSLongitude\":120.58319,\"GPSLongitudeRef\":\"E\",\"Orientation\":8,\"Make\":\"Canon\",\"Model\":\"Canon EOS 5D Mark IV\",\"MD5Original\":\"7d7c6f90ddf41e89b2c03cdb1a71abea\"}",
        "semblance": 0.0,
        "activity_id": 28734,
        "faceCoordLeft": 0,
        "faceCoordTop": 0,
        "faceCoordRight": 0,
        "faceCoordBottom": 0,
        "image_height": 4480,
        "image_width": 6720,
        "media_show_type": 1,
        "status": 1,
        "is_canbuy": 1,
        "standard_price": 100,
        "grade": 0,
        "sortValue": null,
        "searchType": null,
        "gps_latitude": 31.29834,
        "gps_longitude": 120.58319,
        "uid": 127870,
        "orientation": 8
      },
      {
        "id": "5831391554937194410",
        "media_id": "5831391553728579382",
        "url": "https://oss.runnerbar.com/img/watermark/user_upload/origin/20231210/1702176211336_5ad03a93_058e_44b5_9033_48a75fb5a5d6.JPG",
        "url_lq": "https://oss.runnerbar.com/img/watermark/user_upload/origin/20231210/1702176211400_e1fa219f_9f22_4e6b_9f33_3ae7573b6536.JPG",
        "url_hq": "https://oss.runnerbar.com/img/watermark/user_upload/origin/20231210/1702176211089_8d7a0bba_fa4a_4b96_8885_9adde1931c62.JPG",
        "meta_info": "{\"DateTimeOriginal\":\"2023:12:10 09:51:48\",\"ImageHeight\":4480,\"ImageWidth\":6720,\"GPSLatitude\":31.29834,\"GPSLatitudeRef\":\"N\",\"GPSLongitude\":120.58319,\"GPSLongitudeRef\":\"E\",\"Orientation\":8,\"Make\":\"Canon\",\"Model\":\"Canon EOS 5D Mark IV\",\"MD5Original\":\"489870d0ce0d73010407464b9b1f9e6b\"}",
        "semblance": 0.0,
        "activity_id": 28734,
        "faceCoordLeft": 0,
        "faceCoordTop": 0,
        "faceCoordRight": 0,
        "faceCoordBottom": 0,
        "image_height": 4480,
        "image_width": 6720,
        "media_show_type": 1,
        "status": 1,
        "is_canbuy": 1,
        "standard_price": 100,
        "grade": 0,
        "sortValue": null,
        "searchType": null,
        "gps_latitude": 31.29834,
        "gps_longitude": 120.58319,
        "uid": 127870,
        "orientation": 8
      },
      {
        "id": "5831391596309815108",
        "media_id": "5831391595091304283",
        "url": "https://oss.runnerbar.com/img/watermark/user_upload/origin/20231210/1702176212565_814138f1_9059_4098_a40f_3d330cc63fc1.JPG",
        "url_lq": "https://oss.runnerbar.com/img/watermark/user_upload/origin/20231210/1702176212624_b02b55d6_02b4_4e7a_9bda_ee0e0133d5a5.JPG",
        "url_hq": "https://oss.runnerbar.com/img/watermark/user_upload/origin/20231210/1702176212322_99fb31a6_66c2_45a2_be74_16cb3ba0266c.JPG",
        "meta_info": "{\"DateTimeOriginal\":\"2023:12:10 09:51:49\",\"ImageHeight\":4480,\"ImageWidth\":6720,\"GPSLatitude\":31.29834,\"GPSLatitudeRef\":\"N\",\"GPSLongitude\":120.58319,\"GPSLongitudeRef\":\"E\",\"Orientation\":8,\"Make\":\"Canon\",\"Model\":\"Canon EOS 5D Mark IV\",\"MD5Original\":\"0ddbf590e01708ffe5e3cb644d46c4f4\"}",
        "semblance": 0.0,
        "activity_id": 28734,
        "faceCoordLeft": 0,
        "faceCoordTop": 0,
        "faceCoordRight": 0,
        "faceCoordBottom": 0,
        "image_height": 4480,
        "image_width": 6720,
        "media_show_type": 1,
        "status": 1,
        "is_canbuy": 1,
        "standard_price": 100,
        "grade": 0,
        "sortValue": null,
        "searchType": null,
        "gps_latitude": 31.29834,
        "gps_longitude": 120.58319,
        "uid": 127870,
        "orientation": 8
      },
      {
        "id": "5831412041058787265",
        "media_id": "5831412039860854626",
        "url": "https://oss.runnerbar.com/img/watermark/user_upload/origin/20231210/1702176821884_4623b7e5_7e01_4a9d_9fef_aaada9ca8e62.jpg",
        "url_lq": "https://oss.runnerbar.com/img/watermark/user_upload/origin/20231210/1702176821944_527fb71f_b662_4266_ac20_be5fd57ea1e1.jpg",
        "url_hq": "https://oss.runnerbar.com/img/watermark/user_upload/origin/20231210/1702176821623_6d3941be_7143_4a20_893f_9c9882396d91.jpg",
        "meta_info": "{\"DateTimeOriginal\":\"2023:12:10 07:55:41\",\"ImageHeight\":2560,\"ImageWidth\":3840,\"GPSLatitude\":31.29834,\"GPSLatitudeRef\":\"N\",\"GPSLongitude\":120.58319,\"GPSLongitudeRef\":\"E\",\"Orientation\":1,\"Make\":\"Canon\",\"Model\":\"Canon EOS 5D Mark III\",\"MD5Original\":\"4a8005b7eef95a45bde3019159de8862\"}",
        "semblance": 0.0,
        "activity_id": 28734,
        "faceCoordLeft": 0,
        "faceCoordTop": 0,
        "faceCoordRight": 0,
        "faceCoordBottom": 0,
        "image_height": 2560,
        "image_width": 3840,
        "media_show_type": 1,
        "status": 1,
        "is_canbuy": 1,
        "standard_price": 100,
        "grade": 0,
        "sortValue": null,
        "searchType": null,
        "gps_latitude": 31.29834,
        "gps_longitude": 120.58319,
        "uid": 2437228,
        "orientation": 1
      },
      {
        "id": "5831419451789975325",
        "media_id": "5831419450625204158",
        "url": "https://oss.runnerbar.com/img/watermark/user_upload/origin/20231210/1702177042703_79ca8752_2e45_4ecc_a69a_3364e1d74872.jpg",
        "url_lq": "https://oss.runnerbar.com/img/watermark/user_upload/origin/20231210/1702177042768_0c7cec58_2e4e_481a_9482_5c4482095dad.jpg",
        "url_hq": "https://oss.runnerbar.com/img/watermark/user_upload/origin/20231210/1702177042480_3cb5ce12_7070_4b56_a712_1c8365c7c5cf.jpg",
        "meta_info": "{\"DateTimeOriginal\":\"2023:12:10 08:56:31\",\"ImageHeight\":2560,\"ImageWidth\":3840,\"GPSLatitude\":31.29834,\"GPSLatitudeRef\":\"N\",\"GPSLongitude\":120.58319,\"GPSLongitudeRef\":\"E\",\"Orientation\":1,\"Make\":\"Canon\",\"Model\":\"Canon EOS 5D Mark III\",\"MD5Original\":\"bfbe16b615f1fb853122db14547d5fc0\"}",
        "semblance": 0.0,
        "activity_id": 28734,
        "faceCoordLeft": 0,
        "faceCoordTop": 0,
        "faceCoordRight": 0,
        "faceCoordBottom": 0,
        "image_height": 2560,
        "image_width": 3840,
        "media_show_type": 1,
        "status": 1,
        "is_canbuy": 1,
        "standard_price": 100,
        "grade": 0,
        "sortValue": null,
        "searchType": null,
        "gps_latitude": 31.29834,
        "gps_longitude": 120.58319,
        "uid": 2437228,
        "orientation": 1
      },
      {
        "id": "5831419461688526738",
        "media_id": "5831419460511303458",
        "url": "https://oss.runnerbar.com/img/watermark/user_upload/origin/20231210/1702177043019_bb591a86_0cae_4b36_8d76_d96559c42bca.jpg",
        "url_lq": "https://oss.runnerbar.com/img/watermark/user_upload/origin/20231210/1702177043087_1f329e67_d2ef_487a_80ce_672311ed3613.jpg",
        "url_hq": "https://oss.runnerbar.com/img/watermark/user_upload/origin/20231210/1702177042775_1384551b_1b07_4076_9cf7_ed54f2653bd1.jpg",
        "meta_info": "{\"DateTimeOriginal\":\"2023:12:10 08:56:32\",\"ImageHeight\":2560,\"ImageWidth\":3840,\"GPSLatitude\":31.29834,\"GPSLatitudeRef\":\"N\",\"GPSLongitude\":120.58319,\"GPSLongitudeRef\":\"E\",\"Orientation\":1,\"Make\":\"Canon\",\"Model\":\"Canon EOS 5D Mark III\",\"MD5Original\":\"b26d06d92a3d4ba0d48e291e2e5a20ac\"}",
        "semblance": 0.0,
        "activity_id": 28734,
        "faceCoordLeft": 0,
        "faceCoordTop": 0,
        "faceCoordRight": 0,
        "faceCoordBottom": 0,
        "image_height": 2560,
        "image_width": 3840,
        "media_show_type": 1,
        "status": 1,
        "is_canbuy": 1,
        "standard_price": 100,
        "grade": 0,
        "sortValue": null,
        "searchType": null,
        "gps_latitude": 31.29834,
        "gps_longitude": 120.58319,
        "uid": 2437228,
        "orientation": 1
      },
      {
        "id": "5831714688647202638",
        "media_id": "5831714670747354952",
        "url": "https://oss.runnerbar.com/img/watermark/user_upload/origin/20231210/1702185841821_303649dd_a581_4817_94c4_9b0a40a6535e.jpg",
        "url_lq": "https://oss.runnerbar.com/img/watermark/user_upload/origin/20231210/1702185841880_15916cd1_3ed4_49a8_bbbb_880a881a4f28.jpg",
        "url_hq": "https://oss.runnerbar.com/img/watermark/user_upload/origin/20231210/1702185841224_0bf3508d_41a0_4547_83b1_5be487cabf92.jpg",
        "meta_info": "{\"DateTimeOriginal\":\"2023:12:10 09:25:29\",\"ImageHeight\":3016,\"ImageWidth\":4528,\"GPSLatitude\":31.29834,\"GPSLatitudeRef\":\"N\",\"GPSLongitude\":120.58319,\"GPSLongitudeRef\":\"E\",\"Orientation\":6,\"Make\":\"NIKON CORPORATION\",\"Model\":\"NIKON Z 6_2\",\"MD5Original\":\"1cb606136d589ef71959111f257f9d1c\"}",
        "semblance": 0.0,
        "activity_id": 28734,
        "faceCoordLeft": 0,
        "faceCoordTop": 0,
        "faceCoordRight": 0,
        "faceCoordBottom": 0,
        "image_height": 3016,
        "image_width": 4528,
        "media_show_type": 1,
        "status": 1,
        "is_canbuy": 1,
        "standard_price": 100,
        "grade": 0,
        "sortValue": null,
        "searchType": null,
        "gps_latitude": 31.29834,
        "gps_longitude": 120.58319,
        "uid": 1340609,
        "orientation": 6
      },
      {
        "id": "5831714698143112969",
        "media_id": "5831714677727534871",
        "url": "https://oss.runnerbar.com/img/watermark/user_upload/origin/20231210/1702185842090_7c01d655_752c_4a6e_a974_0442b7cd5fb0.jpg",
        "url_lq": "https://oss.runnerbar.com/img/watermark/user_upload/origin/20231210/1702185842154_c9dddcdf_da44_4ca9_9e14_7bfa80240b3c.jpg",
        "url_hq": "https://oss.runnerbar.com/img/watermark/user_upload/origin/20231210/1702185841507_f8b21760_d635_487e_a602_5c2aa78b9bf3.jpg",
        "meta_info": "{\"DateTimeOriginal\":\"2023:12:10 09:25:29\",\"ImageHeight\":3016,\"ImageWidth\":4528,\"GPSLatitude\":31.29834,\"GPSLatitudeRef\":\"N\",\"GPSLongitude\":120.58319,\"GPSLongitudeRef\":\"E\",\"Orientation\":6,\"Make\":\"NIKON CORPORATION\",\"Model\":\"NIKON Z 6_2\",\"MD5Original\":\"af4738a3dca5ccd33f72af83d72a6a47\"}",
        "semblance": 0.0,
        "activity_id": 28734,
        "faceCoordLeft": 0,
        "faceCoordTop": 0,
        "faceCoordRight": 0,
        "faceCoordBottom": 0,
        "image_height": 3016,
        "image_width": 4528,
        "media_show_type": 1,
        "status": 1,
        "is_canbuy": 1,
        "standard_price": 100,
        "grade": 0,
        "sortValue": null,
        "searchType": null,
        "gps_latitude": 31.29834,
        "gps_longitude": 120.58319,
        "uid": 1340609,
        "orientation": 6
      },
      {
        "id": "5831714753172375380",
        "media_id": "5831714734966409034",
        "url": "https://oss.runnerbar.com/img/watermark/user_upload/origin/20231210/1702185843718_48fb2caf_2d05_45ba_9c6e_5a10baee6756.jpg",
        "url_lq": "https://oss.runnerbar.com/img/watermark/user_upload/origin/20231210/1702185843783_0171155f_56f0_47ed_af62_48b528bd61cb.jpg",
        "url_hq": "https://oss.runnerbar.com/img/watermark/user_upload/origin/20231210/1702185843147_67146327_0714_468e_b96c_2366ef0eb51f.jpg",
        "meta_info": "{\"DateTimeOriginal\":\"2023:12:10 09:25:31\",\"ImageHeight\":3016,\"ImageWidth\":4528,\"GPSLatitude\":31.29834,\"GPSLatitudeRef\":\"N\",\"GPSLongitude\":120.58319,\"GPSLongitudeRef\":\"E\",\"Orientation\":6,\"Make\":\"NIKON CORPORATION\",\"Model\":\"NIKON Z 6_2\",\"MD5Original\":\"0ed44ab9aacc978ce80bc76dc4f62f30\"}",
        "semblance": 0.0,
        "activity_id": 28734,
        "faceCoordLeft": 0,
        "faceCoordTop": 0,
        "faceCoordRight": 0,
        "faceCoordBottom": 0,
        "image_height": 3016,
        "image_width": 4528,
        "media_show_type": 1,
        "status": 1,
        "is_canbuy": 1,
        "standard_price": 100,
        "grade": 0,
        "sortValue": null,
        "searchType": null,
        "gps_latitude": 31.29834,
        "gps_longitude": 120.58319,
        "uid": 1340609,
        "orientation": 6
      },
      {
        "id": "5831714841420531706",
        "media_id": "5831714821960861461",
        "url": "https://oss.runnerbar.com/img/watermark/user_upload/origin/20231210/1702185846327_f5d2bbc6_0157_4c9e_b6f0_b8c432dfdcd5.jpg",
        "url_lq": "https://oss.runnerbar.com/img/watermark/user_upload/origin/20231210/1702185846384_a89763ee_2f93_48be_aa3d_4c51b78424f6.jpg",
        "url_hq": "https://oss.runnerbar.com/img/watermark/user_upload/origin/20231210/1702185845777_bca9a9dd_6044_494e_b212_a828da90fbf0.jpg",
        "meta_info": "{\"DateTimeOriginal\":\"2023:12:10 09:25:31\",\"ImageHeight\":3016,\"ImageWidth\":4528,\"GPSLatitude\":31.29834,\"GPSLatitudeRef\":\"N\",\"GPSLongitude\":120.58319,\"GPSLongitudeRef\":\"E\",\"Orientation\":6,\"Make\":\"NIKON CORPORATION\",\"Model\":\"NIKON Z 6_2\",\"MD5Original\":\"b5735b42ed43f7c3cc9981f0f4baa1bd\"}",
        "semblance": 0.0,
        "activity_id": 28734,
        "faceCoordLeft": 0,
        "faceCoordTop": 0,
        "faceCoordRight": 0,
        "faceCoordBottom": 0,
        "image_height": 3016,
        "image_width": 4528,
        "media_show_type": 1,
        "status": 1,
        "is_canbuy": 1,
        "standard_price": 100,
        "grade": 0,
        "sortValue": null,
        "searchType": null,
        "gps_latitude": 31.29834,
        "gps_longitude": 120.58319,
        "uid": 1340609,
        "orientation": 6
      },
      {
        "id": "5831714887423664038",
        "media_id": "5831714868496146339",
        "url": "https://oss.runnerbar.com/img/watermark/user_upload/origin/20231210/1702185847755_30e68b31_157f_4bf9_91be_a8f346c73a84.jpg",
        "url_lq": "https://oss.runnerbar.com/img/watermark/user_upload/origin/20231210/1702185847809_47ef2e51_2511_4b23_9666_718347cfd9ea.jpg",
        "url_hq": "https://oss.runnerbar.com/img/watermark/user_upload/origin/20231210/1702185847148_f3b699dc_f412_49fa_b0ce_e3fc5314ae84.jpg",
        "meta_info": "{\"DateTimeOriginal\":\"2023:12:10 09:25:29\",\"ImageHeight\":3016,\"ImageWidth\":4528,\"GPSLatitude\":31.29834,\"GPSLatitudeRef\":\"N\",\"GPSLongitude\":120.58319,\"GPSLongitudeRef\":\"E\",\"Orientation\":6,\"Make\":\"NIKON CORPORATION\",\"Model\":\"NIKON Z 6_2\",\"MD5Original\":\"b8c49d02b40f24330a285ad99fdfbc29\"}",
        "semblance": 0.0,
        "activity_id": 28734,
        "faceCoordLeft": 0,
        "faceCoordTop": 0,
        "faceCoordRight": 0,
        "faceCoordBottom": 0,
        "image_height": 3016,
        "image_width": 4528,
        "media_show_type": 1,
        "status": 1,
        "is_canbuy": 1,
        "standard_price": 100,
        "grade": 0,
        "sortValue": null,
        "searchType": null,
        "gps_latitude": 31.29834,
        "gps_longitude": 120.58319,
        "uid": 1340609,
        "orientation": 6
      },
      {
        "id": "5831714922018283386",
        "media_id": "5831714901769428854",
        "url": "https://oss.runnerbar.com/img/watermark/user_upload/origin/20231210/1702185848834_59c6b38a_adeb_438d_9375_14dec445304e.jpg",
        "url_lq": "https://oss.runnerbar.com/img/watermark/user_upload/origin/20231210/1702185848895_994aac5e_5007_4960_8d56_782d9601ac61.jpg",
        "url_hq": "https://oss.runnerbar.com/img/watermark/user_upload/origin/20231210/1702185848179_d31415cd_60f6_4c95_811e_278fed910c99.jpg",
        "meta_info": "{\"DateTimeOriginal\":\"2023:12:10 09:25:29\",\"ImageHeight\":3016,\"ImageWidth\":4528,\"GPSLatitude\":31.29834,\"GPSLatitudeRef\":\"N\",\"GPSLongitude\":120.58319,\"GPSLongitudeRef\":\"E\",\"Orientation\":6,\"Make\":\"NIKON CORPORATION\",\"Model\":\"NIKON Z 6_2\",\"MD5Original\":\"b33503cfb65d7bb332a84d78fac43f2c\"}",
        "semblance": 0.0,
        "activity_id": 28734,
        "faceCoordLeft": 0,
        "faceCoordTop": 0,
        "faceCoordRight": 0,
        "faceCoordBottom": 0,
        "image_height": 3016,
        "image_width": 4528,
        "media_show_type": 1,
        "status": 1,
        "is_canbuy": 1,
        "standard_price": 100,
        "grade": 0,
        "sortValue": null,
        "searchType": null,
        "gps_latitude": 31.29834,
        "gps_longitude": 120.58319,
        "uid": 1340609,
        "orientation": 6
      },
      {
        "id": "5831714968122073017",
        "media_id": "5831714948282687355",
        "url": "https://oss.runnerbar.com/img/watermark/user_upload/origin/20231210/1702185850162_7f5969a3_076f_407f_bee0_75e34183d665.jpg",
        "url_lq": "https://oss.runnerbar.com/img/watermark/user_upload/origin/20231210/1702185850220_822ddce2_c788_4ad7_b670_76a3f91be449.jpg",
        "url_hq": "https://oss.runnerbar.com/img/watermark/user_upload/origin/20231210/1702185849553_f7c75cf2_4db4_4930_8605_1b1397c12738.jpg",
        "meta_info": "{\"DateTimeOriginal\":\"2023:12:10 09:25:31\",\"ImageHeight\":3016,\"ImageWidth\":4528,\"GPSLatitude\":31.29834,\"GPSLatitudeRef\":\"N\",\"GPSLongitude\":120.58319,\"GPSLongitudeRef\":\"E\",\"Orientation\":6,\"Make\":\"NIKON CORPORATION\",\"Model\":\"NIKON Z 6_2\",\"MD5Original\":\"69e493163103d9c7cbb76b1aa1df01fa\"}",
        "semblance": 0.0,
        "activity_id": 28734,
        "faceCoordLeft": 0,
        "faceCoordTop": 0,
        "faceCoordRight": 0,
        "faceCoordBottom": 0,
        "image_height": 3016,
        "image_width": 4528,
        "media_show_type": 1,
        "status": 1,
        "is_canbuy": 1,
        "standard_price": 100,
        "grade": 0,
        "sortValue": null,
        "searchType": null,
        "gps_latitude": 31.29834,
        "gps_longitude": 120.58319,
        "uid": 1340609,
        "orientation": 6
      },
      {
        "id": "5831714990905532199",
        "media_id": "5831714970072489944",
        "url": "https://oss.runnerbar.com/img/watermark/user_upload/origin/20231210/1702185850821_be93c3cc_ff34_44d9_bf44_cfffa5e7530f.jpg",
        "url_lq": "https://oss.runnerbar.com/img/watermark/user_upload/origin/20231210/1702185850880_999a4ddf_9da3_49fd_9cd5_4c824d74230a.jpg",
        "url_hq": "https://oss.runnerbar.com/img/watermark/user_upload/origin/20231210/1702185850232_f78f47bf_6c38_4a94_b1d7_e41e668d462f.jpg",
        "meta_info": "{\"DateTimeOriginal\":\"2023:12:10 09:25:31\",\"ImageHeight\":3016,\"ImageWidth\":4528,\"GPSLatitude\":31.29834,\"GPSLatitudeRef\":\"N\",\"GPSLongitude\":120.58319,\"GPSLongitudeRef\":\"E\",\"Orientation\":6,\"Make\":\"NIKON CORPORATION\",\"Model\":\"NIKON Z 6_2\",\"MD5Original\":\"ddf37f01e2c7692706107e27dd7d1a17\"}",
        "semblance": 0.0,
        "activity_id": 28734,
        "faceCoordLeft": 0,
        "faceCoordTop": 0,
        "faceCoordRight": 0,
        "faceCoordBottom": 0,
        "image_height": 3016,
        "image_width": 4528,
        "media_show_type": 1,
        "status": 1,
        "is_canbuy": 1,
        "standard_price": 100,
        "grade": 0,
        "sortValue": null,
        "searchType": null,
        "gps_latitude": 31.29834,
        "gps_longitude": 120.58319,
        "uid": 1340609,
        "orientation": 6
      }
    ],
    "count": 41,
    "base_url": "https://oss.runnerbar.com/",
    "is_open_pay": 1,
    "newTopicInfoList": [],
    "video": 0,
    "game_number": "B30483",
    "has_precise_search_face": 0,
    "bind_face": 1,
    "new_count": 0,
    "face_id": 102764633,
    "other_name": null
  },
  "msg": "ok",
  "order_package_info": {
    "face_id": null,
    "url": null,
    "number_bibs": null,
    "package_name": null,
    "str_hq_coupon_number": null,
    "str_origin_coupon_number": null,
    "str_customized_photos": null,
    "hq_coupon_number": 0,
    "origin_coupon_number": 0,
    "customized_photos": 0
  },
  "status": 0
}